traitlets_paths/__init__.py
traitlets_paths/paths.py
traitlets_paths-0.1.3.dist-info/LICENSE.txt
traitlets_paths-0.1.3.dist-info/METADATA
traitlets_paths-0.1.3.dist-info/RECORD
traitlets_paths-0.1.3.dist-info/WHEEL
traitlets_paths-0.1.3.dist-info/top_level.txt
