Metadata-Version: 2.1
Name: traitlets-paths
Version: 0.1.3
Summary: Traitlets module for pathlib.
Home-page: https://github.com/Zsailer/traitlets_paths
Author: Zach Sailer
Author-email: zachsailer@gmail.com
License: UNKNOWN
Platform: UNKNOWN
Classifier: Programming Language :: Python :: 3.6
Classifier: Programming Language :: Python :: 3.7
Requires-Dist: traitlets
